{
  "2026-05-05": {
    "timestamp": 1777980219.551635,
    "topics": [
      "[The Guardian Global Development] Logging, murder and money:",
      "[Al Jazeera English] Japan\u2019s Takaichi pledges deeper energy ",
      "[Williams Lake Tribune] Cariboo Chilcotin emergency manageme",
      "[IndigiNews] In \u2018B.C.\u2019s\u2019 interior, a syilx program is return",
      "[Williams Lake Tribune] MP Fuhr: Canadian investments in tra",
      "[TechRadar] 'Help cattle producers hold onto their land and ",
      "[Williams Lake Tribune] New cherry varieties developed in Su",
      "[Quartz] BYD's quarterly profit plunged as China's EV price "
    ],
    "themes": [
      "rural development",
      "technology adoption",
      "environmental impact",
      "Indigenous tech"
    ],
    "date": "2026-05-05"
  },
  "2026-05-06": {
    "timestamp": 1778068735.51747,
    "topics": [
      "[New Atlas] Adventure RV mastermind preps VW into \"most ambi",
      "[Tom's Hardware] Inland QN450 1TB SSD Review: Maximum effici",
      "[Tom's Hardware] Lenovo Yoga Slim 7i Aura Edition (2026) Rev",
      "[Hackaday] Sunlight Powered, Sunlight Readable: Solar Case f",
      "[Toms Guide] I got tired of waiting for a touchscreen iMac s",
      "[MacRumors] iPhone 18 Might Look a Lot More Like an 'e' Mode",
      "[New Atlas] Superfast power bank brings its own solar panel ",
      "[Toms Guide] I was skeptical about whether a $1,000 robot la"
    ],
    "themes": [
      "rural development",
      "technology adoption",
      "environmental impact",
      "Indigenous tech"
    ],
    "date": "2026-05-06"
  },
  "2026-05-07": {
    "timestamp": 1778155456.207649,
    "topics": [
      "[The Tyee] BC\u2019s New Chief Treaty Commissioner on the Path Fo",
      "[APTN News] \u2018It\u2019s re-traumatizing\u2019: families of MMIWGT2S+ sa",
      "[APTN News] Ottawa invested $6.5B to First Nations without t",
      "[BC Gov News] Minister\u2019s statement on appointment of provinc",
      "[BC Gov News] Minister\u2019s, parliamentary secretary\u2019s statemen",
      "Coming soon to an event near you",
      "Rethinking Privacy Through Indigenous Data Sovereignty\n    &",
      "Indigenous knowledge can improve AI models to manage fires, "
    ],
    "themes": [
      "rural development",
      "technology adoption",
      "Indigenous tech",
      "connectivity"
    ],
    "date": "2026-05-07"
  },
  "2026-05-08": {
    "timestamp": 1778239423.056829,
    "topics": [
      "[BC Gov News] Day-use passes available for three popular par",
      "[The Tyee] Diary of an Accidental Birder",
      "[New Atlas] Pricey backpacking tent is so light & airy, it's",
      "[CNET] Turtlebox Ranger Bluetooth Speaker Review: Quality So",
      "[Toms Guide] I fell for the hype and got Salomon trail shoes",
      "[New Atlas] Tiny bike camper expands via slide-out to sleep ",
      "[BC Gov News] Supporting B.C. tech to help reduce lightning-",
      "[Williams Lake Tribune] 1 helicopter \u2018bucketing\u2019 water, 14 f"
    ],
    "themes": [
      "rural development",
      "technology adoption",
      "environmental impact",
      "Indigenous tech"
    ],
    "date": "2026-05-08"
  },
  "2026-05-09": {
    "timestamp": 1778324690.511213,
    "topics": [
      "[Williams Lake Tribune] New exhibitions at Williams Lake Sta",
      "[Williams Lake Tribune] Walk held from Williams Lake to Tl\u2019e",
      "[Williams Lake Tribune] Williams Lake cadet builds leadershi",
      "[Williams Lake Tribune] Cariboo\u2019s Margo Wagner stays on as h",
      "[Williams Lake Tribune] Teen hospitalized after vehicle roll",
      "[Williams Lake Tribune] Foundry Cariboo Chilcotin concludes ",
      "[Williams Lake Tribune] Lakers Car Club Spring Round Up Show",
      "[Williams Lake Tribune] Williams Lake council awards tender "
    ],
    "themes": [
      "rural development",
      "technology adoption",
      "Indigenous tech"
    ],
    "date": "2026-05-09"
  },
  "2026-05-10": {
    "timestamp": 1778411201.645518,
    "topics": [
      "[ScienceDaily] What scientists found inside coral reefs coul",
      "[Kottke.org] Animated Artemis II Photos Reveal Satellites Bu",
      "[ScienceAlert] Movement Triggers a Hidden 'Brain Cleaning' M",
      "[NYT Top Stories] New Study Shows Risks of Amazon Deforestat",
      "[ScienceDaily] Scientists make stunning discovery that could",
      "[ScienceDaily] Scientists found the \u201choly grail\u201d gene that c",
      "[ScienceDaily] Evolution isn\u2019t random. Scientists find the s",
      "[ScienceDaily] Scientists just created exotic new forms of m"
    ],
    "themes": [
      "rural development",
      "environmental impact",
      "Indigenous tech"
    ],
    "date": "2026-05-10"
  },
  "2026-05-11": {
    "timestamp": 1778503470.35437,
    "topics": [
      "[NYT Business] James Murdoch\u2019s Company Said to Be in Talks t",
      "[Kottke.org] &#8220;Podcast sloplords&#8221; are  flooding t",
      "[Engadget] Spotify now lets AI agents like OpenClaw generate",
      "[TechRadar] 'Podslop' is a real and growing problem \u2014 data s",
      "[Open Culture] How Yasujir\u014d Ozu Learned to Use Color in His ",
      "#1358 The A.I. App for Rich People to Fight Journalists Who ",
      "#1359 Michelle Rempel Garner is Tired of Conservative Drama ",
      "Discover Our Cell Phone Plans | Fizz"
    ],
    "themes": [
      "rural development",
      "technology adoption",
      "environmental impact",
      "Indigenous tech"
    ],
    "date": "2026-05-11"
  },
  "2026-05-12": {
    "timestamp": 1778587379.597189,
    "topics": [
      "[InsideEVs] While You Stop For A 30-Minute Charge, Nio Just ",
      "[NPR Health News] Forest therapy: Why a physician wants more",
      "[InsideEVs] BMW Has Built Way More EVs Than You Think",
      "[Toms Guide] A $340,000 bonus isn't enough \u2014 Samsung workers",
      "[The Narwhal] Inside Haida Gwaii\u2019s historic plan to ditch di",
      "[New Atlas] Startup harnesses the power of AI in the ongoing",
      "[Quartz] USDA is giving California peach farmers $9 million ",
      "[Williams Lake Tribune] $12M coming from province to support"
    ],
    "themes": [
      "rural development",
      "technology adoption",
      "environmental impact",
      "Indigenous tech"
    ],
    "date": "2026-05-12"
  },
  "2026-05-13": {
    "timestamp": 1778674402.814872,
    "topics": [
      "[Tom's Hardware] Louis Rossmann tells 3D printer maker Bambu",
      "[Tom's Hardware] 3DMakerPro Toucan 3D Scanner review: All-in",
      "[CNET] This 4-Tool Head 3D Printer Is So Much Fun I Gave It ",
      "[Hackaday] Trying to Fix a GoPro Hero 10 With No Camera Inpu",
      "[Hackaday] Multimaterial SLA Printer Will Make Your Head Spi",
      "Skiing on Jet Power",
      "Skiing on Jet Power",
      "Skiing on Jet Power"
    ],
    "themes": [
      "rural development",
      "technology adoption",
      "environmental impact",
      "Indigenous tech"
    ],
    "date": "2026-05-13"
  },
  "2026-05-14": {
    "timestamp": 1778759941.2986,
    "topics": [
      "[The Tyee] BC\u2019s New Chief Treaty Commissioner on the Path Fo",
      "[The Guardian Global Development] Official marking of land f",
      "[Global News] Manitoba\u2019s nursing regulator apologizes for di",
      "[APTN News] UN advice raises pressure on Liberals to end Ind",
      "[IndigiNews] IndigiNews is now a registered charity!",
      "Soaring from coast to coast for Indspire",
      "Soaring from coast to coast for Indspire",
      "Digital pathways into the University Art Collections"
    ],
    "themes": [
      "rural development",
      "technology adoption",
      "environmental impact",
      "Indigenous tech"
    ],
    "date": "2026-05-14"
  },
  "2026-05-15": {
    "timestamp": 1778846635.761153,
    "topics": [
      "[Resilience.org] Environmental protection depends on more th",
      "[100 Mile Free Press] CARIBOO OUTDOORS: When the breakup fin",
      "[Williams Lake Tribune] Help B.C. communities recover from w",
      "[Resilience.org] Rebuilding after wildfire: Paradise, Califo",
      "[Kottke.org] A very good, very 2026 headline:  Japan Runs Ou",
      "[Williams Lake Tribune] UPDATE: Wildfire in Chasm Provincial",
      "[Williams Lake Tribune] B.C. residents urged to prepare for ",
      "[Boing Boing] Yellowstone grizzly introduces two hikers to t"
    ],
    "themes": [
      "rural development",
      "technology adoption",
      "environmental impact",
      "Indigenous tech"
    ],
    "date": "2026-05-15"
  },
  "2026-05-16": {
    "timestamp": 1778929766.844274,
    "topics": [
      "[100 Mile Free Press] HANSEN: Lac La Hache Community Club pr",
      "[Williams Lake Tribune] 2025 Williams Lake Fire Department r",
      "[Williams Lake Tribune] Williams Lake mayor unhappy with res",
      "[Williams Lake Tribune] Traditional powwow honouring familie",
      "[Williams Lake Tribune] Delegation recognizes Laker\u2019s Go Bus",
      "[Williams Lake Tribune] PHOTOS: Cariboo Chilcotin Youth Fidd",
      "[Williams Lake Tribune] Central Chilcotin Rehabilitation Ltd",
      "[Williams Lake Tribune] Williams Lake fighters return from s"
    ],
    "themes": [
      "rural development",
      "environmental impact",
      "Indigenous tech"
    ],
    "date": "2026-05-16"
  },
  "2026-05-17": {
    "timestamp": 1779016374.346819,
    "topics": [
      "[ScienceDaily] Stunning 150-million-year-old stegosaur skull",
      "[ScienceDaily] Paleontology rocked by discovery of organic m",
      "[New Atlas] JWST discovers a galaxy that doesn\u2019t spin in the",
      "[ScienceDaily] After 100 years, scientists finally uncover h",
      "[ScienceDaily] Scientists discover the Southern Ocean is \u201csw",
      "[ScienceDaily] Giant squid discovery uncovers a hidden deep-",
      "[ScienceDaily] Earth is flying through ancient supernova deb",
      "[New Atlas] Plants may literally hear the sound of approachi"
    ],
    "themes": [
      "rural development",
      "technology adoption",
      "environmental impact",
      "Indigenous tech"
    ],
    "date": "2026-05-17"
  },
  "2026-05-18": {
    "timestamp": 1779114124.354106,
    "topics": [
      "[TechCrunch] Wirestock raises $23M to supply creative multi-",
      "[Open Culture] When the Nobel Prize Committee Rejected The L",
      "[Hackaday] Mixapps: The Mixtape of The Internet Age",
      "[Neowin] Spotify will soon support Apple's technology to ope",
      "[The Tyee] We\u2019re Only Human. And That\u2019ll Do",
      "[NPR Health News] Engaging with the arts can slow biological",
      "[TechRadar] \u201cI cannot divorce the two\u201d: How Star Wars is ble",
      "[IndigiNews] A new GyaaG\u0332ang (totem pole) is raised in Haida"
    ],
    "themes": [
      "rural development",
      "technology adoption",
      "Indigenous tech"
    ],
    "date": "2026-05-18"
  },
  "2026-05-19": {
    "timestamp": 1779196557.289099,
    "topics": [
      "[Williams Lake Tribune] Environmental advocates call pipelin",
      "[Williams Lake Tribune] Wild world record broken by barefoot",
      "[NYT Business] A Start-Up Aiming to Make Geothermal Energy M",
      "[ScienceDaily] Scientists just unlocked a cheaper way to mak",
      "[Hackaday] RS-485 Sprinkler Control: Scaling Irrigation Acro",
      "[New Atlas] Genetic discovery could change how rice is grown",
      "[TechRadar] US data centers use enough electricity to power ",
      "[Tom's Hardware] OpenClaw creator burned through $1.3 millio"
    ],
    "themes": [
      "rural development",
      "technology adoption",
      "environmental impact",
      "Indigenous tech"
    ],
    "date": "2026-05-19"
  },
  "2026-05-20": {
    "timestamp": 1779280959.099454,
    "topics": [
      "[Hackaday] Turning a Junk Laptop Screen Into a Portable Moni",
      "[Hackaday] Using a Nintendo Switch to Speed Up a 3D Printer",
      "[Hackaday] preFlight Slicer Brings Added Part Strength Featu",
      "[Hackaday] Y-zipper: 3D Printing Flexible\u2013Rigid Transition M",
      "[Hackaday] 21st Century Punch Cards are 3D Printed and Read ",
      "[Hackaday] Teardown: ChargeTab Emergency Phone Charger",
      "[How-To Geek] 4 3D printer upgrades you can build with a $5 ",
      "[Tom's Hardware] Louis Rossmann taunts Bambu Lab by hosting "
    ],
    "themes": [
      "rural development",
      "technology adoption",
      "environmental impact",
      "connectivity"
    ],
    "date": "2026-05-20"
  },
  "2026-05-21": {
    "timestamp": 1779367907.065201,
    "topics": [
      "Technology shouldn't sacrifice the integrity of knowledge",
      "Seattle University School of Law Hosts Conference on Indigen",
      "[Williams Lake Tribune] Heiltsuk Nation settles Coquitlam Ca",
      "[CNET] Scientists Warn AI Slop Is Wreaking Havoc in the Rese",
      "[WIRED] A Bipartisan Amendment Would End Police License Plat",
      "#1362 The Truth About Residential School Graves",
      "#181 Avi Lewis: the Canadaland Interview",
      "Discover Our Cell Phone Plans | Fizz"
    ],
    "themes": [
      "rural development",
      "technology adoption",
      "Indigenous tech"
    ],
    "date": "2026-05-21"
  },
  "2026-05-22": {
    "timestamp": 1779452769.580673,
    "topics": [
      "[New Atlas] Winnebago Ram 4x4 camper truck swings for fences",
      "[Williams Lake Tribune] Conservation service investigates no",
      "[WIRED] California\u2019s Wildfire Season Is Already Overactive",
      "[ScienceDaily] Scientists use DNA from poop to save the worl",
      "[Resilience.org] Wide boundary news: Sacrificing wilderness,",
      "[My East Kootenay Now] Grizzly and cubs spotted near Westsid",
      "[Williams Lake Tribune] Province readies wildfire damaged Sh",
      "[BC Gov News] Supporting outdoor recreation, communities, lo"
    ],
    "themes": [
      "rural development",
      "technology adoption",
      "environmental impact",
      "Indigenous tech"
    ],
    "date": "2026-05-22"
  },
  "2026-05-23": {
    "timestamp": 1779535045.179295,
    "topics": [
      "[Williams Lake Tribune] Williams Lake RCMP seek witnesses af",
      "[Williams Lake Tribune] Cariboo drivers reminded to use caut",
      "[Williams Lake Tribune] Planning underway for National Indig",
      "[Williams Lake Tribune] Early blooms for Williams Lake Harve",
      "[Williams Lake Tribune] Williams Lake RCMP urge safe off-roa",
      "[My Cariboo Now] Man arrested in Walmart Parking lot in Ques",
      "[My Cariboo Now] Movie night in Lebourdais Park in Quesnel i",
      "[Williams Lake Tribune] Cariboo Chilcotin MLA endorses Peter"
    ],
    "themes": [
      "rural development",
      "Indigenous tech",
      "connectivity"
    ],
    "date": "2026-05-23"
  },
  "2026-05-24": {
    "timestamp": 1779621851.975763,
    "topics": [
      "[ScienceDaily] Quantum ghost imaging works using only sunlig",
      "[New Atlas] Historical accidents show just how long 'forever",
      "[ScienceDaily] Scientists found a hidden Alzheimer\u2019s trigger",
      "[ScienceAlert] WATCH: A Spacecraft Is Launching to Study How",
      "[ScienceDaily] Ancient lost ocean may have built Central Asi",
      "[ScienceDaily] Plant believed extinct for 60 years suddenly ",
      "[New Atlas] Watch: Daredevil fish climb 50-foot waterfall in",
      "[ScienceAlert] 80% of Earth's Rivers Are Quickly Losing Oxyg"
    ],
    "themes": [
      "rural development",
      "technology adoption",
      "environmental impact",
      "connectivity"
    ],
    "date": "2026-05-24"
  },
  "2026-05-25": {
    "timestamp": 1779716240.939621,
    "topics": [
      "[Kottke.org] How to Make a Living as an Artist",
      "[Android Authority] Project Genie now lets you reimagine you",
      "[The Verge] Spotify Studio&#8217;s AI agent creates a daily ",
      "[Boing Boing] Sci-Hub and Libgen descend from a Soviet tradi",
      "[TechRadar] Spotify's huge new podcast makeover means you ca",
      "#1366 Death of a Journalist: Remembering Elaine Dewar",
      "#182 The Canadian Defence Gold Rush",
      "Discover Our Cell Phone Plans | Fizz"
    ],
    "themes": [
      "rural development",
      "technology adoption",
      "environmental impact",
      "Indigenous tech"
    ],
    "date": "2026-05-25"
  }
}